opticiq/__init__.py
opticiq/bg.py
opticiq/data.py
opticiq/edge.py
opticiq/grad.py
opticiq/math.py
opticiq/mtf.py
opticiq/peak.py
opticiq/recipes.py
opticiq/roi.py
opticiq/gen/__init__.py
opticiq/gen/chart.py
opticiq/gen/extra.py
opticiq/gen/gauss.py
opticiq/gen/model.py
opticiq/gen/star.py
opticiq/opt/__init__.py
opticiq/opt/fft.py
opticiq-0.1.0.dist-info/licenses/LICENSE
opticiq-0.1.0.dist-info/METADATA
opticiq-0.1.0.dist-info/WHEEL
opticiq-0.1.0.dist-info/top_level.txt
opticiq-0.1.0.dist-info/RECORD
