Metadata-Version: 2.4
Name: opticiq
Version: 0.1.0
Summary: Optical Image Quality and Beam Tests routines
Author-email: Chris Cannon <chris.cannon.9001@gmail.com>
License: BSD-2-Clause
Project-URL: Homepage, https://github.com/chriscannon9001/opticiq
Requires-Python: >=3.7
License-File: LICENSE
Requires-Dist: numpy
Requires-Dist: matplotlib
Requires-Dist: PIllow
Requires-Dist: scikit-image
Requires-Dist: sympy
Requires-Dist: more-itertools; python_version < "3.10"
Provides-Extra: test
Requires-Dist: pytest; extra == "test"
Provides-Extra: extras
Requires-Dist: gdstk; extra == "extras"
Requires-Dist: reportlab; extra == "extras"
Dynamic: license-file
